{
    "title": "Marilyn Miglin Destiny Blue Eau de Parfum Duo",
    "description": "For More Info or to Buy Now: http:\/\/www.hsn.com\/products\/seo\/8382179?rdr=1&sourceid=youtube&cm_mmc=Social-_-Youtube-_-ProductVideo-_-548069\r\nMarilyn Miglin Destiny Blue Eau de Parfum Duo \nYour fragrance says something about you. Make a statement in the sparkling freshness of clementine and bergamot with subdued tones of amberwood. The...\r\nPrices shown on the previously recorded video may not represent the current price.  View hsn.com to view the current selling price. HSN Item #548069",
    "referenceId": "bfschx2bI1s",
    "date_created": "1493388236",
    "date_modified": "1503417913",
    "tags": "",
    "sourceId": "4",
    "VIDEO_LENGTH": "LONG",
    "duration": "417",
    "status": "approved",
    "visibility": "1",
    "VV_VI": null,
    "CVV_VI": null,
    "engagement_score": null,
    "conversion_score": null,
    "style": null,
    "living": null,
    "category6": null,
    "series": null,
    "video_type": null,
    "storefront": null,
    "gemstone_guide": null,
    "id": "112338458",
    "loginId": "1758927",
    "entityType": "1",
    "titleTextEncoded": "Marilyn-Miglin-Destiny-Blue-Eau-de-Parfum-Duo",
    "category": "",
    "settings": "",
    "asset": {
        "type": "youtube",
        "thumbnailUrl": "https:\/\/i.ytimg.com\/vi\/bfschx2bI1s\/hqdefault.jpg",
        "uploadDate": 1493388236,
        "videoId": "bfschx2bI1s",
        "title": "Marilyn Miglin Destiny Blue Eau de Parfum Duo",
        "description": "For More Info or to Buy Now: http:\/\/www.hsn.com\/products\/seo\/8382179?rdr=1&sourceid=youtube&cm_mmc=Social-_-Youtube-_-ProductVideo-_-548069\r\nMarilyn Miglin Destiny Blue Eau de Parfum Duo \nYour fragrance says something about you. Make a statement in the sparkling freshness of clementine and bergamot with subdued tones of amberwood. The...\r\nPrices shown on the previously recorded video may not represent the current price.  View hsn.com to view the current selling price. HSN Item #548069",
        "author": "HSNtv",
        "mediaDuration": 417,
        "prettyDuration": "00:06:57",
        "views": "23"
    },
    "transcripts": "",
    "metrics_statistics": "",
    "tvp_profiles": [
        "4"
    ],
    "tvp_profiles_manual": "",
    "tvp_profiles_maxscore": 16356.544,
    "tvp_profiles_nlp": null,
    "tvp_profiles_account": [
        "123"
    ],
    "tvp_profiles_manual_account": null,
    "tvp_profiles_maxscore_account": 37536.473
}