{
    "title": "StarFire Prints Disney Glass Ornament",
    "description": "For More Info or to Buy Now: http:\/\/www.hsn.com\/products\/seo\/8191072?rdr=1&sourceid=youtube&cm_mmc=Social-_-Youtube-_-ProductVideo-_-083343\r\nStarFire Prints Disney Circular Glass Ornament  The Little Mermaid  \nBring the magic of The Little Mermaid to your window or holiday dcor with this collectible glass ornament. Featuring Thomas...\r\nPrices shown on the previously recorded video may not represent the current price.  View hsn.com to view the current selling price. HSN Item #083343",
    "referenceId": "9eXiWjHIwHs",
    "date_created": "1471009128",
    "date_modified": "1503421909",
    "tags": "",
    "sourceId": "4",
    "VIDEO_LENGTH": "LONG",
    "duration": "348",
    "status": "approved",
    "visibility": "1",
    "VV_VI": null,
    "CVV_VI": null,
    "engagement_score": null,
    "conversion_score": null,
    "style": null,
    "living": null,
    "category6": null,
    "series": null,
    "video_type": null,
    "storefront": null,
    "gemstone_guide": null,
    "id": "112361546",
    "loginId": "1758927",
    "entityType": "1",
    "titleTextEncoded": "StarFire-Prints-Disney-Glass-Ornament",
    "category": "",
    "settings": "",
    "asset": {
        "type": "youtube",
        "thumbnailUrl": "https:\/\/i.ytimg.com\/vi\/9eXiWjHIwHs\/hqdefault.jpg",
        "uploadDate": 1471009128,
        "videoId": "9eXiWjHIwHs",
        "title": "StarFire Prints Disney Glass Ornament",
        "description": "For More Info or to Buy Now: http:\/\/www.hsn.com\/products\/seo\/8191072?rdr=1&sourceid=youtube&cm_mmc=Social-_-Youtube-_-ProductVideo-_-083343\r\nStarFire Prints Disney Circular Glass Ornament  The Little Mermaid  \nBring the magic of The Little Mermaid to your window or holiday dcor with this collectible glass ornament. Featuring Thomas...\r\nPrices shown on the previously recorded video may not represent the current price.  View hsn.com to view the current selling price. HSN Item #083343",
        "author": "HSNtv",
        "mediaDuration": 348,
        "prettyDuration": "00:05:48",
        "views": "375"
    },
    "transcripts": "",
    "metrics_statistics": "",
    "tvp_profiles": [
        "18",
        "20",
        "28"
    ],
    "tvp_profiles_manual": "",
    "tvp_profiles_maxscore": 1652.6727,
    "tvp_profiles_nlp": null,
    "tvp_profiles_account": [
        "258"
    ],
    "tvp_profiles_manual_account": null,
    "tvp_profiles_maxscore_account": 18829.967
}