{
    "title": "Emma Fox Leather Embroidered GeoFloral Handbag Strap",
    "description": "For More Info or to Buy Now: http:\/\/www.hsn.com\/products\/seo\/8277573?rdr=1&sourceid=youtube&cm_mmc=Social-_-Youtube-_-ProductVideo-_-075667\r\nEmma Fox Genuine Leather Embroidered GeoFloral Handbag Strap  \nSwitch up your handbag aesthetic with a strap that's Earthy vibe features embroidered flowers. It's the perfect way to go from your...\r\nPrices shown on the previously recorded video may not represent the current price.  View hsn.com to view the current selling price. HSN Item #075667",
    "referenceId": "a-UeyDs7bqc",
    "date_created": "1490135914",
    "date_modified": "1504059703",
    "tags": "",
    "sourceId": "4",
    "VIDEO_LENGTH": "SHORT",
    "duration": "161",
    "status": "approved",
    "visibility": "1",
    "VV_VI": "1",
    "CVV_VI": null,
    "engagement_score": null,
    "conversion_score": null,
    "style": null,
    "living": null,
    "category6": null,
    "series": null,
    "video_type": null,
    "storefront": null,
    "gemstone_guide": null,
    "id": "112341266",
    "loginId": "1758927",
    "entityType": "1",
    "titleTextEncoded": "Emma-Fox-Leather-Embroidered-GeoFloral-Handbag-Strap",
    "category": "",
    "settings": "",
    "asset": {
        "type": "youtube",
        "thumbnailUrl": "https:\/\/i.ytimg.com\/vi\/a-UeyDs7bqc\/hqdefault.jpg",
        "uploadDate": 1490135914,
        "videoId": "a-UeyDs7bqc",
        "title": "Emma Fox Leather Embroidered GeoFloral Handbag Strap",
        "description": "For More Info or to Buy Now: http:\/\/www.hsn.com\/products\/seo\/8277573?rdr=1&sourceid=youtube&cm_mmc=Social-_-Youtube-_-ProductVideo-_-075667\r\nEmma Fox Genuine Leather Embroidered GeoFloral Handbag Strap  \nSwitch up your handbag aesthetic with a strap that's Earthy vibe features embroidered flowers. It's the perfect way to go from your...\r\nPrices shown on the previously recorded video may not represent the current price.  View hsn.com to view the current selling price. HSN Item #075667",
        "author": "HSNtv",
        "mediaDuration": 161,
        "prettyDuration": "00:02:41",
        "views": "17"
    },
    "transcripts": "",
    "metrics_statistics": {
        "VV_VI": {
            "lastUpdatedDate": "2017-11-17"
        }
    },
    "tvp_profiles": [
        "28"
    ],
    "tvp_profiles_manual": "",
    "tvp_profiles_maxscore": 7272.5596,
    "tvp_profiles_nlp": null,
    "tvp_profiles_account": [
        "1468"
    ],
    "tvp_profiles_manual_account": null,
    "tvp_profiles_maxscore_account": 15256.749
}