{
    "title": "Perfect Sense 10pack Toaster Bags",
    "description": "For More Info or to Buy Now: http:\/\/www.hsn.com\/products\/seo\/8210138?rdr=1&sourceid=youtube&cm_mmc=Social-_-Youtube-_-ProductVideo-_-507303\r\nPerfect Sense 10pack Toaster Bags  \nTurn your toaster into a grill with Theresa Scotto's innovative toaster bags. Quickly prepare toasted sandwiches, chicken nuggets, pizza and more. They're...\r\nPrices shown on the previously recorded video may not represent the current price.  View hsn.com to view the current selling price. HSN Item #507303",
    "referenceId": "7F30nDg0ubw",
    "date_created": "1484137625",
    "date_modified": "1503419596",
    "tags": "",
    "sourceId": "4",
    "VIDEO_LENGTH": "LONG",
    "duration": "372",
    "status": "approved",
    "visibility": "1",
    "VV_VI": null,
    "CVV_VI": null,
    "engagement_score": null,
    "conversion_score": null,
    "style": null,
    "living": null,
    "category6": null,
    "series": null,
    "video_type": null,
    "storefront": null,
    "gemstone_guide": null,
    "id": "112348402",
    "loginId": "1758927",
    "entityType": "1",
    "titleTextEncoded": "Perfect-Sense-10pack-Toaster-Bags",
    "category": "",
    "settings": "",
    "asset": {
        "type": "youtube",
        "thumbnailUrl": "https:\/\/i.ytimg.com\/vi\/7F30nDg0ubw\/hqdefault.jpg",
        "uploadDate": 1484137625,
        "videoId": "7F30nDg0ubw",
        "title": "Perfect Sense 10pack Toaster Bags",
        "description": "For More Info or to Buy Now: http:\/\/www.hsn.com\/products\/seo\/8210138?rdr=1&sourceid=youtube&cm_mmc=Social-_-Youtube-_-ProductVideo-_-507303\r\nPerfect Sense 10pack Toaster Bags  \nTurn your toaster into a grill with Theresa Scotto's innovative toaster bags. Quickly prepare toasted sandwiches, chicken nuggets, pizza and more. They're...\r\nPrices shown on the previously recorded video may not represent the current price.  View hsn.com to view the current selling price. HSN Item #507303",
        "author": "HSNtv",
        "mediaDuration": 372,
        "prettyDuration": "00:06:12",
        "views": "23"
    },
    "transcripts": "",
    "metrics_statistics": "",
    "tvp_profiles": [
        "14"
    ],
    "tvp_profiles_manual": "",
    "tvp_profiles_maxscore": 7234.122,
    "tvp_profiles_nlp": null,
    "tvp_profiles_account": [
        "210"
    ],
    "tvp_profiles_manual_account": null,
    "tvp_profiles_maxscore_account": 12855.125
}