{
    "title": "Heidi Daus \"Jeweled Jester\" Enamel and Crystal Pin",
    "description": "For More Info or to Buy Now: http:\/\/www.hsn.com\/products\/seo\/7027161?rdr=1&sourceid=youtube&cm_mmc=Social-_-Youtube-_-ProductVideo-_-234754\r\nHeidi Daus \"Jeweled Jester\" Enamel and Crystal Pin\nEntertain the masses with this applauseworthy \"Jeweled Jester\" brooch. An eccentric costume with motley patterns of cream and black enamel is...\r\nPrices shown on the previously recorded video may not represent the current price.  View hsn.com to view the current selling price. HSN Item #234754",
    "referenceId": "ImOQ4-85Dik",
    "date_created": "1494971136",
    "date_modified": "1503417646",
    "tags": "",
    "sourceId": "4",
    "VIDEO_LENGTH": "SHORT",
    "duration": "197",
    "status": "approved",
    "visibility": "1",
    "VV_VI": null,
    "CVV_VI": null,
    "engagement_score": null,
    "conversion_score": null,
    "style": null,
    "living": null,
    "category6": null,
    "series": null,
    "video_type": null,
    "storefront": null,
    "gemstone_guide": null,
    "id": "112336559",
    "loginId": "1758927",
    "entityType": "1",
    "titleTextEncoded": "Heidi-Daus-Jeweled-Jester-Enamel-and-Crystal-Pin",
    "category": "",
    "settings": "",
    "asset": {
        "type": "youtube",
        "thumbnailUrl": "https:\/\/i.ytimg.com\/vi\/ImOQ4-85Dik\/hqdefault.jpg",
        "uploadDate": 1494971136,
        "videoId": "ImOQ4-85Dik",
        "title": "Heidi Daus \"Jeweled Jester\" Enamel and Crystal Pin",
        "description": "For More Info or to Buy Now: http:\/\/www.hsn.com\/products\/seo\/7027161?rdr=1&sourceid=youtube&cm_mmc=Social-_-Youtube-_-ProductVideo-_-234754\r\nHeidi Daus \"Jeweled Jester\" Enamel and Crystal Pin\nEntertain the masses with this applauseworthy \"Jeweled Jester\" brooch. An eccentric costume with motley patterns of cream and black enamel is...\r\nPrices shown on the previously recorded video may not represent the current price.  View hsn.com to view the current selling price. HSN Item #234754",
        "author": "HSNtv",
        "mediaDuration": 197,
        "prettyDuration": "00:03:17",
        "views": "17"
    },
    "transcripts": "",
    "metrics_statistics": "",
    "tvp_profiles": [
        "20"
    ],
    "tvp_profiles_manual": "",
    "tvp_profiles_maxscore": 14353.71,
    "tvp_profiles_nlp": null,
    "tvp_profiles_account": [
        "154"
    ],
    "tvp_profiles_manual_account": null,
    "tvp_profiles_maxscore_account": 15745.624
}