{
    "title": "PRAI Ageless Face Forward Creme  2oz",
    "description": "For More Info or to Buy Now: http:\/\/www.hsn.com\/products\/seo\/7802773?rdr=1&sourceid=youtube&cm_mmc=Social-_-Youtube-_-ProductVideo-_-431817\r\nPRAI Ageless Face Forward Creme  2oz \nProgress it's what humans are known for. We take the old and transform the look of it for a fresh new future. Be a part of the tradition with this formula...\r\nPrices shown on the previously recorded video may not represent the current price.  View hsn.com to view the current selling price. HSN Item #431817",
    "referenceId": "WnWpMokly8M",
    "date_created": "1452669017",
    "date_modified": "1503424662",
    "tags": "",
    "sourceId": "4",
    "VIDEO_LENGTH": "LONG",
    "duration": "323",
    "status": "approved",
    "visibility": "1",
    "VV_VI": null,
    "CVV_VI": null,
    "engagement_score": null,
    "conversion_score": null,
    "style": null,
    "living": null,
    "category6": null,
    "series": null,
    "video_type": null,
    "storefront": null,
    "gemstone_guide": null,
    "id": "112383262",
    "loginId": "1758927",
    "entityType": "1",
    "titleTextEncoded": "PRAI-Ageless-Face-Forward-Creme-2oz",
    "category": "",
    "settings": "",
    "asset": {
        "type": "youtube",
        "thumbnailUrl": "https:\/\/i.ytimg.com\/vi\/WnWpMokly8M\/hqdefault.jpg",
        "uploadDate": 1452669017,
        "videoId": "WnWpMokly8M",
        "title": "PRAI Ageless Face Forward Creme  2oz",
        "description": "For More Info or to Buy Now: http:\/\/www.hsn.com\/products\/seo\/7802773?rdr=1&sourceid=youtube&cm_mmc=Social-_-Youtube-_-ProductVideo-_-431817\r\nPRAI Ageless Face Forward Creme  2oz \nProgress it's what humans are known for. We take the old and transform the look of it for a fresh new future. Be a part of the tradition with this formula...\r\nPrices shown on the previously recorded video may not represent the current price.  View hsn.com to view the current selling price. HSN Item #431817",
        "author": "HSNtv",
        "mediaDuration": 323,
        "prettyDuration": "00:05:23",
        "views": "219"
    },
    "transcripts": "",
    "metrics_statistics": "",
    "tvp_profiles": [
        "18",
        "9",
        "28"
    ],
    "tvp_profiles_manual": "",
    "tvp_profiles_maxscore": 2090.4546,
    "tvp_profiles_nlp": null,
    "tvp_profiles_account": [
        "96"
    ],
    "tvp_profiles_manual_account": null,
    "tvp_profiles_maxscore_account": 11541.24
}