{
    "title": "Sevilla Silver with Technibond 3Stone Drop 18\" Necklace",
    "description": "For More Info or to Buy Now: http:\/\/www.hsn.com\/products\/seo\/8285283?rdr=1&sourceid=youtube&cm_mmc=Social-_-Youtube-_-ProductVideo-_-524892\r\nSevilla Silver with Technibond 3Stone Drop 18\" Necklace \nTake one yellow Technibond chain, add your choice of 1, 2 or 3 gemstone charms, and what do you get? A beautiful multitone metallic...\r\nPrices shown on the previously recorded video may not represent the current price.  View hsn.com to view the current selling price. HSN Item #524892",
    "referenceId": "DaXJGyNNi6I",
    "date_created": "1492097291",
    "date_modified": "1503418228",
    "tags": "",
    "sourceId": "4",
    "VIDEO_LENGTH": "SHORT",
    "duration": "182",
    "status": "approved",
    "visibility": "1",
    "VV_VI": null,
    "CVV_VI": null,
    "engagement_score": null,
    "conversion_score": null,
    "style": null,
    "living": null,
    "category6": null,
    "series": null,
    "video_type": null,
    "storefront": null,
    "gemstone_guide": null,
    "id": "112339975",
    "loginId": "1758927",
    "entityType": "1",
    "titleTextEncoded": "Sevilla-Silver-with-Technibond-3Stone-Drop-18-Necklace",
    "category": "",
    "settings": "",
    "asset": {
        "type": "youtube",
        "thumbnailUrl": "https:\/\/i.ytimg.com\/vi\/DaXJGyNNi6I\/hqdefault.jpg",
        "uploadDate": 1492097291,
        "videoId": "DaXJGyNNi6I",
        "title": "Sevilla Silver with Technibond 3Stone Drop 18\" Necklace",
        "description": "For More Info or to Buy Now: http:\/\/www.hsn.com\/products\/seo\/8285283?rdr=1&sourceid=youtube&cm_mmc=Social-_-Youtube-_-ProductVideo-_-524892\r\nSevilla Silver with Technibond 3Stone Drop 18\" Necklace \nTake one yellow Technibond chain, add your choice of 1, 2 or 3 gemstone charms, and what do you get? A beautiful multitone metallic...\r\nPrices shown on the previously recorded video may not represent the current price.  View hsn.com to view the current selling price. HSN Item #524892",
        "author": "HSNtv",
        "mediaDuration": 182,
        "prettyDuration": "00:03:02",
        "views": "30"
    },
    "transcripts": "",
    "metrics_statistics": "",
    "tvp_profiles": [
        "20"
    ],
    "tvp_profiles_manual": "",
    "tvp_profiles_maxscore": 24364.014,
    "tvp_profiles_nlp": null,
    "tvp_profiles_account": [
        "116"
    ],
    "tvp_profiles_manual_account": null,
    "tvp_profiles_maxscore_account": 24962.139
}