{
    "title": "Winix WiFi Enabled NK105 Air Purifier",
    "description": "For More Info or to Buy Now: http:\/\/www.hsn.com\/products\/seo\/8146572?rdr=1&sourceid=youtube&cm_mmc=Social-_-Youtube-_-ProductVideo-_-495769\r\nWinix WiFi Enabled NK105 Air Purifier \nDay and night, the air you breathe matters, so savor a breath of cleaner air with this WiFi enabled air purifier. Its True HEPA filtration captures 99.97% of...\r\nPrices shown on the previously recorded video may not represent the current price.  View hsn.com to view the current selling price. HSN Item #495769",
    "referenceId": "rRjKyB5lWwY",
    "date_created": "1494105421",
    "date_modified": "1504059757",
    "tags": "",
    "sourceId": "4",
    "VIDEO_LENGTH": "LONG",
    "duration": "982",
    "status": "approved",
    "visibility": "1",
    "VV_VI": null,
    "CVV_VI": null,
    "engagement_score": null,
    "conversion_score": null,
    "style": null,
    "living": null,
    "category6": null,
    "series": null,
    "video_type": null,
    "storefront": null,
    "gemstone_guide": null,
    "id": "112337640",
    "loginId": "1758927",
    "entityType": "1",
    "titleTextEncoded": "Winix-WiFi-Enabled-NK105-Air-Purifier",
    "category": "",
    "settings": "",
    "asset": {
        "type": "youtube",
        "thumbnailUrl": "https:\/\/i.ytimg.com\/vi\/rRjKyB5lWwY\/hqdefault.jpg",
        "uploadDate": 1494105421,
        "videoId": "rRjKyB5lWwY",
        "title": "Winix WiFi Enabled NK105 Air Purifier",
        "description": "For More Info or to Buy Now: http:\/\/www.hsn.com\/products\/seo\/8146572?rdr=1&sourceid=youtube&cm_mmc=Social-_-Youtube-_-ProductVideo-_-495769\r\nWinix WiFi Enabled NK105 Air Purifier \nDay and night, the air you breathe matters, so savor a breath of cleaner air with this WiFi enabled air purifier. Its True HEPA filtration captures 99.97% of...\r\nPrices shown on the previously recorded video may not represent the current price.  View hsn.com to view the current selling price. HSN Item #495769",
        "author": "HSNtv",
        "mediaDuration": 982,
        "prettyDuration": "00:16:22",
        "views": "95"
    },
    "transcripts": "",
    "metrics_statistics": "",
    "tvp_profiles": [
        "18"
    ],
    "tvp_profiles_manual": "",
    "tvp_profiles_maxscore": 9676.118,
    "tvp_profiles_nlp": null,
    "tvp_profiles_account": [
        "215"
    ],
    "tvp_profiles_manual_account": null,
    "tvp_profiles_maxscore_account": 13346.927
}