{
    "title": "Sevilla Silver Byzantine Link Collar 18\" Necklace",
    "description": "For More Info or to Buy Now: http:\/\/www.hsn.com\/products\/seo\/8250564?rdr=1&sourceid=youtube&cm_mmc=Social-_-Youtube-_-ProductVideo-_-516288\r\nSevilla Silver with Technibond Graduated Byzantine Link Collar Necklace\nIsn't it time you embraced the classics? Intricate Byzantine links never go out of style, and this modern collarstyle...\r\nPrices shown on the previously recorded video may not represent the current price.  View hsn.com to view the current selling price. HSN Item #516288",
    "referenceId": "7s9L9WtDrnY",
    "date_created": "1483086293",
    "date_modified": "1503419837",
    "tags": "",
    "sourceId": "4",
    "VIDEO_LENGTH": "SHORT",
    "duration": "174",
    "status": "approved",
    "visibility": "1",
    "VV_VI": null,
    "CVV_VI": null,
    "engagement_score": null,
    "conversion_score": null,
    "style": null,
    "living": null,
    "category6": null,
    "series": null,
    "video_type": null,
    "storefront": null,
    "gemstone_guide": null,
    "id": "112349675",
    "loginId": "1758927",
    "entityType": "1",
    "titleTextEncoded": "Sevilla-Silver-Byzantine-Link-Collar-18-Necklace",
    "category": "",
    "settings": "",
    "asset": {
        "type": "youtube",
        "thumbnailUrl": "https:\/\/i.ytimg.com\/vi\/7s9L9WtDrnY\/hqdefault.jpg",
        "uploadDate": 1483086293,
        "videoId": "7s9L9WtDrnY",
        "title": "Sevilla Silver Byzantine Link Collar 18\" Necklace",
        "description": "For More Info or to Buy Now: http:\/\/www.hsn.com\/products\/seo\/8250564?rdr=1&sourceid=youtube&cm_mmc=Social-_-Youtube-_-ProductVideo-_-516288\r\nSevilla Silver with Technibond Graduated Byzantine Link Collar Necklace\nIsn't it time you embraced the classics? Intricate Byzantine links never go out of style, and this modern collarstyle...\r\nPrices shown on the previously recorded video may not represent the current price.  View hsn.com to view the current selling price. HSN Item #516288",
        "author": "HSNtv",
        "mediaDuration": 174,
        "prettyDuration": "00:02:54",
        "views": "10"
    },
    "transcripts": "",
    "metrics_statistics": "",
    "tvp_profiles": [
        "20",
        "34"
    ],
    "tvp_profiles_manual": "",
    "tvp_profiles_maxscore": 5369.7964,
    "tvp_profiles_nlp": null,
    "tvp_profiles_account": [
        "152"
    ],
    "tvp_profiles_manual_account": null,
    "tvp_profiles_maxscore_account": 10339.322
}