{
    "title": "Debbie Meyer Genius Twist   Core 3piece Set",
    "description": "For More Info or to Buy Now: http:\/\/www.hsn.com\/products\/seo\/8279131?rdr=1&sourceid=youtube&cm_mmc=Social-_-Youtube-_-ProductVideo-_-523445\r\nDebbie Meyer Genius Twist   Core 3piece Set  \nLooking for some creative and delicious new twists on appetizers, main dishes and desserts? The patentpending Debbie Meyer Genius Twist   Core set...\r\nPrices shown on the previously recorded video may not represent the current price.  View hsn.com to view the current selling price. HSN Item #523445",
    "referenceId": "cMlbrAXVhDs",
    "date_created": "1499113814",
    "date_modified": "1504059703",
    "tags": "",
    "sourceId": "4",
    "VIDEO_LENGTH": "LONG",
    "duration": "638",
    "status": "approved",
    "visibility": "1",
    "VV_VI": null,
    "CVV_VI": null,
    "engagement_score": null,
    "conversion_score": null,
    "style": null,
    "living": null,
    "category6": null,
    "series": null,
    "video_type": null,
    "storefront": null,
    "gemstone_guide": null,
    "id": "112331320",
    "loginId": "1758927",
    "entityType": "1",
    "titleTextEncoded": "Debbie-Meyer-Genius-Twist-Core-3piece-Set",
    "category": "",
    "settings": "",
    "asset": {
        "type": "youtube",
        "thumbnailUrl": "https:\/\/i.ytimg.com\/vi\/cMlbrAXVhDs\/hqdefault.jpg",
        "uploadDate": 1499113814,
        "videoId": "cMlbrAXVhDs",
        "title": "Debbie Meyer Genius Twist   Core 3piece Set",
        "description": "For More Info or to Buy Now: http:\/\/www.hsn.com\/products\/seo\/8279131?rdr=1&sourceid=youtube&cm_mmc=Social-_-Youtube-_-ProductVideo-_-523445\r\nDebbie Meyer Genius Twist   Core 3piece Set  \nLooking for some creative and delicious new twists on appetizers, main dishes and desserts? The patentpending Debbie Meyer Genius Twist   Core set...\r\nPrices shown on the previously recorded video may not represent the current price.  View hsn.com to view the current selling price. HSN Item #523445",
        "author": "HSNtv",
        "mediaDuration": 638,
        "prettyDuration": "00:10:38",
        "views": "61"
    },
    "transcripts": "",
    "metrics_statistics": "",
    "tvp_profiles": [
        "18"
    ],
    "tvp_profiles_manual": "",
    "tvp_profiles_maxscore": 5743.8154,
    "tvp_profiles_nlp": null,
    "tvp_profiles_account": [
        "126"
    ],
    "tvp_profiles_manual_account": null,
    "tvp_profiles_maxscore_account": 4985.778
}