{
    "title": "PRAI Ageless Throat Ionic System with Throat   Decolleta...",
    "description": "For More Info or to Buy Now: http:\/\/www.hsn.com\/products\/seo\/8067798?rdr=1&sourceid=youtube&cm_mmc=Social-_-Youtube-_-ProductVideo-_-482697\r\nPRAI Ageless Throat Ionic System with Throat   Decolletage Creme \nRamp up your beauty routine with this ionic throat kit and accompanying cream for your throat and decolletage. The application...\r\nPrices shown on the previously recorded video may not represent the current price.  View hsn.com to view the current selling price. HSN Item #482697",
    "referenceId": "0sbLb88jUic",
    "date_created": "1466211843",
    "date_modified": "1503422540",
    "tags": "",
    "sourceId": "4",
    "VIDEO_LENGTH": "LONG",
    "duration": "1048",
    "status": "approved",
    "visibility": "1",
    "VV_VI": null,
    "CVV_VI": null,
    "engagement_score": null,
    "conversion_score": null,
    "style": null,
    "living": null,
    "category6": null,
    "series": null,
    "video_type": null,
    "storefront": null,
    "gemstone_guide": null,
    "id": "112365291",
    "loginId": "1758927",
    "entityType": "1",
    "titleTextEncoded": "PRAI-Ageless-Throat-Ionic-System-with-Throat-Decolleta",
    "category": "",
    "settings": "",
    "asset": {
        "type": "youtube",
        "thumbnailUrl": "https:\/\/i.ytimg.com\/vi\/0sbLb88jUic\/hqdefault.jpg",
        "uploadDate": 1466211843,
        "videoId": "0sbLb88jUic",
        "title": "PRAI Ageless Throat Ionic System with Throat   Decolleta...",
        "description": "For More Info or to Buy Now: http:\/\/www.hsn.com\/products\/seo\/8067798?rdr=1&sourceid=youtube&cm_mmc=Social-_-Youtube-_-ProductVideo-_-482697\r\nPRAI Ageless Throat Ionic System with Throat   Decolletage Creme \nRamp up your beauty routine with this ionic throat kit and accompanying cream for your throat and decolletage. The application...\r\nPrices shown on the previously recorded video may not represent the current price.  View hsn.com to view the current selling price. HSN Item #482697",
        "author": "HSNtv",
        "mediaDuration": 1048,
        "prettyDuration": "00:17:28",
        "views": "918"
    },
    "transcripts": "",
    "metrics_statistics": "",
    "tvp_profiles": [
        "18",
        "26",
        "12"
    ],
    "tvp_profiles_manual": "",
    "tvp_profiles_maxscore": 4117.676,
    "tvp_profiles_nlp": null,
    "tvp_profiles_account": [
        "218"
    ],
    "tvp_profiles_manual_account": null,
    "tvp_profiles_maxscore_account": 38564.95
}