{
    "title": "Margo Manhattan \"Liquid Hearts\" Hoop Earrings",
    "description": "For More Info or to Buy Now: http:\/\/www.hsn.com\/products\/seo\/8371718?rdr=1&sourceid=youtube&cm_mmc=Social-_-Youtube-_-ProductVideo-_-545148\r\nMargo Manhattan \"Liquid Hearts\" Sterling Silver Hoop Earrings\nMargo loves hearts! That's why you see them in so many of her creations. These fun, flirty hoops feature a river of hearts, strung...\r\nPrices shown on the previously recorded video may not represent the current price.  View hsn.com to view the current selling price. HSN Item #545148",
    "referenceId": "7KyPDifuIC0",
    "date_created": "1495163845",
    "date_modified": "1503417566",
    "tags": "",
    "sourceId": "4",
    "VIDEO_LENGTH": "SHORT",
    "duration": "194",
    "status": "approved",
    "visibility": "1",
    "VV_VI": null,
    "CVV_VI": null,
    "engagement_score": null,
    "conversion_score": null,
    "style": null,
    "living": null,
    "category6": null,
    "series": null,
    "video_type": null,
    "storefront": null,
    "gemstone_guide": null,
    "id": "112336305",
    "loginId": "1758927",
    "entityType": "1",
    "titleTextEncoded": "Margo-Manhattan-Liquid-Hearts-Hoop-Earrings",
    "category": "",
    "settings": "",
    "asset": {
        "type": "youtube",
        "thumbnailUrl": "https:\/\/i.ytimg.com\/vi\/7KyPDifuIC0\/hqdefault.jpg",
        "uploadDate": 1495163845,
        "videoId": "7KyPDifuIC0",
        "title": "Margo Manhattan \"Liquid Hearts\" Hoop Earrings",
        "description": "For More Info or to Buy Now: http:\/\/www.hsn.com\/products\/seo\/8371718?rdr=1&sourceid=youtube&cm_mmc=Social-_-Youtube-_-ProductVideo-_-545148\r\nMargo Manhattan \"Liquid Hearts\" Sterling Silver Hoop Earrings\nMargo loves hearts! That's why you see them in so many of her creations. These fun, flirty hoops feature a river of hearts, strung...\r\nPrices shown on the previously recorded video may not represent the current price.  View hsn.com to view the current selling price. HSN Item #545148",
        "author": "HSNtv",
        "mediaDuration": 194,
        "prettyDuration": "00:03:14",
        "views": "24"
    },
    "transcripts": "",
    "metrics_statistics": "",
    "tvp_profiles": [
        "20"
    ],
    "tvp_profiles_manual": "",
    "tvp_profiles_maxscore": 11100.083,
    "tvp_profiles_nlp": null,
    "tvp_profiles_account": [
        "146"
    ],
    "tvp_profiles_manual_account": null,
    "tvp_profiles_maxscore_account": 7845.379
}