{
    "title": "Connected Life with Mark Hager Part 2",
    "description": "Aging expert Mark Hager discusses tips and tricks for staying safe in and around your home as you age.\nShop HSN Connected Life at https:\/\/goo.gl\/sjTNLP\nLearn how to get connected.",
    "referenceId": "S1YUMXl6d5w",
    "date_created": "1506714695",
    "date_modified": "1507568383",
    "tags": "",
    "sourceId": "4",
    "VIDEO_LENGTH": "SHORT",
    "duration": "191",
    "status": "approved",
    "visibility": "1",
    "VV_VI": "6",
    "CVV_VI": null,
    "engagement_score": null,
    "conversion_score": null,
    "style": null,
    "living": null,
    "category6": null,
    "series": null,
    "video_type": "how_to_inspiration",
    "storefront": "connected_life1",
    "gemstone_guide": null,
    "id": "120397653",
    "loginId": "1758927",
    "entityType": "1",
    "titleTextEncoded": "HSN-Connected-Life-Mark-Hager-Part-2",
    "category": "",
    "settings": "",
    "asset": {
        "type": "youtube",
        "thumbnailUrl": "https:\/\/i.ytimg.com\/vi\/S1YUMXl6d5w\/maxresdefault.jpg",
        "uploadDate": 1506714695,
        "videoId": "S1YUMXl6d5w",
        "title": "HSN | Connected Life: Mark Hager Part 2",
        "description": "Shop HSN Connected Life at https:\/\/goo.gl\/sjTNLP\n\nLearn how to get connected.",
        "author": "HSN",
        "mediaDuration": 191,
        "prettyDuration": "00:03:11",
        "views": "4",
        "uploadAsset": false,
        "quality": ""
    },
    "transcripts": "",
    "metrics_statistics": {
        "VV_VI": {
            "lastUpdatedDate": "2017-12-08"
        }
    },
    "tvp_profiles": [
        "16"
    ],
    "tvp_profiles_manual": "",
    "tvp_profiles_maxscore": 8687.862,
    "tvp_profiles_nlp": null,
    "tvp_profiles_account": [
        "405"
    ],
    "tvp_profiles_manual_account": null,
    "tvp_profiles_maxscore_account": 594.27325
}