{
    "title": "The Monday Night Show with Adam Freeman 10.02.2017 - 08 PM",
    "description": "Adam Freeman shares products and electronic items by Joy Mangano, RCA Tablets and more  for you on the Monday Night Show.",
    "referenceId": "O-HPM8vzltE",
    "date_created": "1506999060",
    "date_modified": "1507302232",
    "tags": "",
    "sourceId": "4",
    "VIDEO_LENGTH": "LONG",
    "duration": "3599",
    "status": "approved",
    "visibility": "1",
    "VV_VI": "4",
    "CVV_VI": null,
    "engagement_score": null,
    "conversion_score": null,
    "style": null,
    "living": null,
    "category6": null,
    "series": "monday_night_show",
    "video_type": null,
    "storefront": null,
    "gemstone_guide": null,
    "id": "120827640",
    "loginId": "1758927",
    "entityType": "1",
    "titleTextEncoded": "HSN-The-Monday-Night-Show-with-Adam-Freeman-10-02-2017-08-PM",
    "category": "",
    "settings": "",
    "asset": {
        "type": "youtube",
        "thumbnailUrl": "https:\/\/i.ytimg.com\/vi\/O-HPM8vzltE\/maxresdefault.jpg",
        "uploadDate": 1506999060,
        "videoId": "O-HPM8vzltE",
        "title": "HSN | The Monday Night Show with Adam Freeman 10.02.2017 - 08 PM",
        "description": "Don't miss a moment of the fun every Monday night from 7pm to 9pm ET only on HSN and HSN.com.  http:\/\/goo.gl\/DjNZaA #n# Prices shown on the previously recorded video may not represent the current price. View hsn.com to view the current selling price.\r Prices shown on the previously recorded video may not represent the current price.  View hsn.com to view the current selling price.SHOP NOW http:\/\/www.hsn.com",
        "author": "HSNtv",
        "mediaDuration": 3599,
        "prettyDuration": "00:59:59",
        "views": "59",
        "uploadAsset": false,
        "quality": ""
    },
    "transcripts": "",
    "metrics_statistics": {
        "VV_VI": {
            "lastUpdatedDate": "2018-01-07"
        }
    },
    "tvp_profiles": [
        "32",
        "33",
        "25"
    ],
    "tvp_profiles_manual": "",
    "tvp_profiles_maxscore": 4037.4143,
    "tvp_profiles_nlp": null,
    "tvp_profiles_account": [
        "719"
    ],
    "tvp_profiles_manual_account": null,
    "tvp_profiles_maxscore_account": 327.1607
}