{
    "title": "Calcium-Magnesium Intensive Care",
    "description": "Support and maintain bone health with our gentle, pure and natural formula. Provides superior forms of the two most abundant minerals found in your bones (Calcium and Magnesium), along with Vitamins C and D3, and Boron.\n\nShop all Andrew Lessman on HSN.com: https:\/\/www.hsn.com\/shop\/andrew-lessman\/129",
    "referenceId": "k_AFoiV6bTw",
    "date_created": "1507655456",
    "date_modified": "1508091707",
    "tags": "",
    "sourceId": "4",
    "VIDEO_LENGTH": "SHORT",
    "duration": "114",
    "status": "approved",
    "visibility": "1",
    "VV_VI": "165",
    "CVV_VI": "70",
    "engagement_score": "1",
    "conversion_score": null,
    "style": null,
    "living": null,
    "category6": null,
    "series": null,
    "video_type": "quicklook",
    "storefront": null,
    "gemstone_guide": null,
    "id": "122329519",
    "loginId": "1758927",
    "entityType": "1",
    "titleTextEncoded": "Calcium-Magnesium-Intensive-Care",
    "category": null,
    "settings": null,
    "asset": {
        "type": "youtube",
        "author": "HSNtv",
        "hdvFlag": 0,
        "description": "Calcium-Magnesium Intensive Care",
        "tags": "",
        "thumbnailUrl": "https:\/\/i.ytimg.com\/vi\/k_AFoiV6bTw\/sddefault.jpg",
        "videoId": "k_AFoiV6bTw",
        "mediaDuration": 114,
        "prettyDuration": "00:01:54",
        "uploadAsset": false,
        "quality": ""
    },
    "transcripts": null,
    "metrics_statistics": "{\"VV_VI\":{\"engagement_score\":{\"lastUpdatedDate\":\"2017-10-20\"}},\"CVV_VI\":{\"conversion_score\":{\"lastUpdatedDate\":\"2017-11-17\"}}}",
    "tvp_profiles": null,
    "tvp_profiles_manual": null,
    "tvp_profiles_maxscore": null,
    "tvp_profiles_nlp": null,
    "tvp_profiles_account": [
        "100"
    ],
    "tvp_profiles_manual_account": null,
    "tvp_profiles_maxscore_account": 1096.1448
}