{
    "title": "Creating Blooming Cards with Anna Griffin",
    "description": "Anna Griffin shows how to create and decorate a blooming card craft. Shop HSN Crafts & Sewing at https:\/\/goo.gl\/5d0Gya",
    "referenceId": "t4PcjISS-qY",
    "date_created": "1489167976",
    "date_modified": "1499780901",
    "tags": "",
    "sourceId": "4",
    "VIDEO_LENGTH": "SHORT",
    "duration": "35",
    "status": "approved",
    "visibility": "1",
    "VV_VI": "80",
    "CVV_VI": "8",
    "engagement_score": "1",
    "conversion_score": "1",
    "style": null,
    "living": "crafts1",
    "category6": "crafts",
    "series": null,
    "video_type": null,
    "storefront": null,
    "gemstone_guide": null,
    "id": "91792239",
    "loginId": "1758927",
    "entityType": "1",
    "titleTextEncoded": "HSN-Good-Crafts-Fast-Anna-Griffin-Creating-Blooming-Cards",
    "category": "",
    "settings": "",
    "asset": {
        "type": "youtube",
        "thumbnailUrl": "https:\/\/i.ytimg.com\/vi\/t4PcjISS-qY\/hqdefault.jpg",
        "uploadDate": 1489167976,
        "videoId": "t4PcjISS-qY",
        "title": "HSN | Good Crafts Fast: Anna Griffin Creating Blooming Cards",
        "description": "Shop HSN Crafts & Sewing at https:\/\/goo.gl\/5d0Gya",
        "author": "HSN",
        "mediaDuration": 35,
        "prettyDuration": "00:00:35",
        "views": "311",
        "uploadAsset": false,
        "quality": ""
    },
    "transcripts": "",
    "metrics_statistics": {
        "VV_VI": {
            "lastUpdatedDate": "2018-01-10"
        }
    },
    "tvp_profiles": [
        "15"
    ],
    "tvp_profiles_manual": true,
    "tvp_profiles_maxscore": 822.7517,
    "tvp_profiles_nlp": null,
    "tvp_profiles_account": [
        "159"
    ],
    "tvp_profiles_manual_account": null,
    "tvp_profiles_maxscore_account": 3130.4749
}